wizart/vision/__init__.py
wizart/vision/_client_enums.py
wizart/vision/_utils.py
wizart/vision/computer_vision_client.py
wizart_vision-1.0.6.dist-info/METADATA
wizart_vision-1.0.6.dist-info/WHEEL
wizart_vision-1.0.6.dist-info/top_level.txt
wizart_vision-1.0.6.dist-info/RECORD
