Metadata-Version: 2.1
Name: wizart-vision
Version: 1.0.6
Summary: Wizart Computer Vision SDK
Author: Yauheni Dzirvuk
Author-email: yauheni.dzirvuk@wizart.ai
License: MIT License
Requires-Dist: numpy >=1.19.2
Requires-Dist: Pillow >=8.0.0
Requires-Dist: requests
Requires-Dist: validators
